{
   "test": "ntp_url_web",
   "url": "http://www.educa.madrid.org/ies.elpinar.alcorcon",
   "delta_sg": 0.310084,
   "cabeceras": {
      "Date": "Wed, 28 May 2025 19:23:23 GMT",
      "Server": "Apache",
      "X-Powered-By": "PHP/8.2.25",
      "Link": "<https://site.educa.madrid.org/ies.elpinar.alcorcon/index.php/wp-json/>; rel=\"https://api.w.org/\", <https://site.educa.madrid.org/ies.elpinar.alcorcon/index.php/wp-json/wp/v2/pages/187>; rel=\"alternate\"; title=\"JSON\"; type=\"application/json\", <https://site.educa.madrid.org/ies.elpinar.alcorcon/>; rel=shortlink",
      "Set-Cookie": "wc_session_ids[default]=8faa098bb8c0811bebd51bfb3aed5636a2f03916; expires=Wed, 28 May 2025 19:31:43 GMT; Max-Age=500; path=/ies.elpinar.alcorcon/; secure; HttpOnly, wc_session_ids[all_forms]=1f31df21ed0149c5fcaaf8534457f3bdcd54fa7e; expires=Wed, 28 May 2025 19:31:43 GMT; Max-Age=500; path=/ies.elpinar.alcorcon/; secure; HttpOnly, wc_session_ids[multi][0]=e23edf525dbfe13aa48f69184224288b72a6103c; expires=Wed, 28 May 2025 19:31:43 GMT; Max-Age=500; path=/ies.elpinar.alcorcon/, wc_session_ids[multi][1]=5112a6efc037ded788ede33e2eb4067399ee7629; expires=Wed, 28 May 2025 19:31:43 GMT; Max-Age=500; path=/ies.elpinar.alcorcon/, wc_session_ids[multi][2]=1d64b88818b1967fc71b1a90facc719cfa05ba77; expires=Wed, 28 May 2025 19:31:43 GMT; Max-Age=500; path=/ies.elpinar.alcorcon/, wc_session_ids[multi][3]=ed3559b83634fe02341a5e0656b3bee64e4c2cb2; expires=Wed, 28 May 2025 19:31:43 GMT; Max-Age=500; path=/ies.elpinar.alcorcon/, wc_session_ids[multi][4]=b02964f4bd788848e56df08121e483156ba68dba; expires=Wed, 28 May 2025 19:31:43 GMT; Max-Age=500; path=/ies.elpinar.alcorcon/",
      "Vary": "Accept-Encoding",
      "Content-Encoding": "gzip",
      "Keep-Alive": "timeout=5, max=99",
      "Connection": "Keep-Alive",
      "Content-Type": "text/html; charset=UTF-8",
      "Strict-Transport-Security": "max-age=15552000",
      "Content-Length": "38413"
   }
}