{
   "test": "ntp_url_web",
   "url": "http://www.educa.madrid.org/ies.avenidadelostor.madrid",
   "delta_sg": -5.688858,
   "cabeceras": {
      "Date": "Thu, 05 Jun 2025 21:17:27 GMT",
      "Server": "Apache",
      "X-Powered-By": "PHP/8.2.25",
      "Link": "<https://site.educa.madrid.org/ies.avenidadelostor.madrid/index.php/wp-json/>; rel=\"https://api.w.org/\", <https://site.educa.madrid.org/ies.avenidadelostor.madrid/index.php/wp-json/wp/v2/pages/140>; rel=\"alternate\"; title=\"JSON\"; type=\"application/json\", <https://site.educa.madrid.org/ies.avenidadelostor.madrid/>; rel=shortlink",
      "Set-Cookie": "wc_session_ids[default]=503537eda469bfa48bb4ffe0c143064014eecd98; expires=Thu, 05 Jun 2025 21:25:47 GMT; Max-Age=500; path=/ies.avenidadelostor.madrid/; secure; HttpOnly, wc_session_ids[all_forms]=73dbfd1732f04108cc155058b8988a3a3ff77af5; expires=Thu, 05 Jun 2025 21:25:47 GMT; Max-Age=500; path=/ies.avenidadelostor.madrid/; secure; HttpOnly, wc_session_ids[multi][0]=439d9ea7767866c7969fea012e64c2143c34b0ff; expires=Thu, 05 Jun 2025 21:25:47 GMT; Max-Age=500; path=/ies.avenidadelostor.madrid/, wc_session_ids[multi][1]=3c047aea255c62c0e273e7e4b0fd08faf4b45ee1; expires=Thu, 05 Jun 2025 21:25:47 GMT; Max-Age=500; path=/ies.avenidadelostor.madrid/, wc_session_ids[multi][2]=c66b1b5ec529f4c30c6e4e3cde9934e560bb5c2b; expires=Thu, 05 Jun 2025 21:25:47 GMT; Max-Age=500; path=/ies.avenidadelostor.madrid/, wc_session_ids[multi][3]=b4e5b4d906e95e4bed7efc5928252681837b971b; expires=Thu, 05 Jun 2025 21:25:47 GMT; Max-Age=500; path=/ies.avenidadelostor.madrid/, wc_session_ids[multi][4]=ce8119a723669606bb8deaa187ace219920cb5e3; expires=Thu, 05 Jun 2025 21:25:47 GMT; Max-Age=500; path=/ies.avenidadelostor.madrid/",
      "Vary": "Accept-Encoding",
      "Content-Encoding": "gzip",
      "Keep-Alive": "timeout=5, max=99",
      "Connection": "Keep-Alive",
      "Content-Type": "text/html; charset=UTF-8",
      "Strict-Transport-Security": "max-age=15552000",
      "Content-Length": "38202"
   }
}