{
   "test": "ntp_url_web",
   "url": "http://www.educa.madrid.org/ies.calatalifa.villaviciosa",
   "delta_sg": -0.244033,
   "cabeceras": {
      "Date": "Thu, 22 May 2025 21:16:22 GMT",
      "Server": "Apache",
      "X-Powered-By": "PHP/8.2.25",
      "Link": "<https://site.educa.madrid.org/ies.calatalifa.villaviciosa/index.php/wp-json/>; rel=\"https://api.w.org/\", <https://site.educa.madrid.org/ies.calatalifa.villaviciosa/index.php/wp-json/wp/v2/pages/5664>; rel=\"alternate\"; title=\"JSON\"; type=\"application/json\", <https://site.educa.madrid.org/ies.calatalifa.villaviciosa/>; rel=shortlink",
      "Set-Cookie": "wc_session_ids[default]=ce2d751397c2da059728eec21a39f912c9880f4f; expires=Thu, 22 May 2025 21:24:42 GMT; Max-Age=500; path=/ies.calatalifa.villaviciosa/; secure; HttpOnly, wc_session_ids[all_forms]=f630ae8eabd6fb13eb1fc9d84485df9bb220baed; expires=Thu, 22 May 2025 21:24:42 GMT; Max-Age=500; path=/ies.calatalifa.villaviciosa/; secure; HttpOnly, wc_session_ids[multi][0]=32231dd4ed2fd0082e0e65de49f5dd53b9056eaf; expires=Thu, 22 May 2025 21:24:42 GMT; Max-Age=500; path=/ies.calatalifa.villaviciosa/, wc_session_ids[multi][1]=12b345e0b5ae5ff13c9ba05d90d6e7c55ecb16d6; expires=Thu, 22 May 2025 21:24:42 GMT; Max-Age=500; path=/ies.calatalifa.villaviciosa/, wc_session_ids[multi][2]=02b5a0340c8153b8b6f640f401de880848dea274; expires=Thu, 22 May 2025 21:24:42 GMT; Max-Age=500; path=/ies.calatalifa.villaviciosa/, wc_session_ids[multi][3]=880cc0e2ee51e143a00e40106d41a967f8ae8848; expires=Thu, 22 May 2025 21:24:42 GMT; Max-Age=500; path=/ies.calatalifa.villaviciosa/, wc_session_ids[multi][4]=19fb65d926dfae7a15ce1bd07f7d022d0e6cd050; expires=Thu, 22 May 2025 21:24:42 GMT; Max-Age=500; path=/ies.calatalifa.villaviciosa/",
      "Vary": "Accept-Encoding",
      "Content-Encoding": "gzip",
      "Keep-Alive": "timeout=5, max=99",
      "Connection": "Keep-Alive",
      "Content-Type": "text/html; charset=UTF-8",
      "Strict-Transport-Security": "max-age=15552000",
      "Content-Length": "51711"
   }
}