{
   "test": "ntp_url_web",
   "url": "http://www.educa.madrid.org/ies.mariadezayas.majadahonda",
   "delta_sg": 0.588103,
   "cabeceras": {
      "Date": "Mon, 24 Feb 2025 14:47:43 GMT",
      "Server": "Apache",
      "X-Powered-By": "PHP/8.2.25",
      "Link": "<https://site.educa.madrid.org/ies.mariadezayas.majadahonda/index.php/wp-json/>; rel=\"https://api.w.org/\", <https://site.educa.madrid.org/ies.mariadezayas.majadahonda/index.php/wp-json/wp/v2/pages/29>; rel=\"alternate\"; type=\"application/json\", <https://site.educa.madrid.org/ies.mariadezayas.majadahonda/>; rel=shortlink",
      "Set-Cookie": "wc_session_ids[default]=2037300f732371695584a5e28e8b1ac04eeddb23; expires=Mon, 24 Feb 2025 14:56:03 GMT; Max-Age=500; path=/ies.mariadezayas.majadahonda/; secure; HttpOnly, wc_session_ids[all_forms]=7ff24764d8cab27766d52e4a292f7d14839ae835; expires=Mon, 24 Feb 2025 14:56:03 GMT; Max-Age=500; path=/ies.mariadezayas.majadahonda/; secure; HttpOnly, wc_session_ids[multi][0]=33a28ccc81828a49b13bf3532037f5e2ca05e5da; expires=Mon, 24 Feb 2025 14:56:03 GMT; Max-Age=500; path=/ies.mariadezayas.majadahonda/, wc_session_ids[multi][1]=1ed378e08ad14dcee63bae7321f4e6fae176df54; expires=Mon, 24 Feb 2025 14:56:03 GMT; Max-Age=500; path=/ies.mariadezayas.majadahonda/, wc_session_ids[multi][2]=bcb9e00174a0fa3555c1a229f4d1e86dee825ccd; expires=Mon, 24 Feb 2025 14:56:03 GMT; Max-Age=500; path=/ies.mariadezayas.majadahonda/, wc_session_ids[multi][3]=484edaa89c3462887b4ce383b33a4f7b9f92297d; expires=Mon, 24 Feb 2025 14:56:03 GMT; Max-Age=500; path=/ies.mariadezayas.majadahonda/, wc_session_ids[multi][4]=c867df90cbe6acbd6fc271b8eb6ee5ec87c2add4; expires=Mon, 24 Feb 2025 14:56:03 GMT; Max-Age=500; path=/ies.mariadezayas.majadahonda/",
      "Vary": "Accept-Encoding",
      "Content-Encoding": "gzip",
      "Keep-Alive": "timeout=5, max=99",
      "Connection": "Keep-Alive",
      "Content-Type": "text/html; charset=UTF-8",
      "Strict-Transport-Security": "max-age=15552000",
      "Content-Length": "46383"
   }
}