{
   "test": "ntp_url_web",
   "url": "http://www.educa.madrid.org/ies.sanagustin.sanagustin",
   "delta_sg": 1.494917,
   "cabeceras": {
      "Date": "Fri, 02 May 2025 16:14:12 GMT",
      "Server": "Apache",
      "X-Powered-By": "PHP/8.2.25",
      "Link": "<https://site.educa.madrid.org/ies.sanagustin.sanagustin/index.php/wp-json/>; rel=\"https://api.w.org/\"",
      "Set-Cookie": "wc_session_ids[default]=6ac198f243eed47fd71b866ee1fbc0e834950ad7; expires=Fri, 02 May 2025 16:22:32 GMT; Max-Age=500; path=/ies.sanagustin.sanagustin/; secure; HttpOnly, wc_session_ids[all_forms]=41740e7d20f49958e20fe3e81ee78ed9adab1eee; expires=Fri, 02 May 2025 16:22:32 GMT; Max-Age=500; path=/ies.sanagustin.sanagustin/; secure; HttpOnly, wc_session_ids[multi][0]=b743d3899a3a93bdb7b8d8ab3fdac4ae79eecc4d; expires=Fri, 02 May 2025 16:22:32 GMT; Max-Age=500; path=/ies.sanagustin.sanagustin/, wc_session_ids[multi][1]=cd0ea2ae2cd106e836d031f36a171ad324b31565; expires=Fri, 02 May 2025 16:22:32 GMT; Max-Age=500; path=/ies.sanagustin.sanagustin/, wc_session_ids[multi][2]=5e1a89632b30dfda8e145d38f35b074af9cdbfda; expires=Fri, 02 May 2025 16:22:32 GMT; Max-Age=500; path=/ies.sanagustin.sanagustin/, wc_session_ids[multi][3]=38ab95f2693bf3e8f972d09eb8f79608f780592b; expires=Fri, 02 May 2025 16:22:32 GMT; Max-Age=500; path=/ies.sanagustin.sanagustin/, wc_session_ids[multi][4]=14a73665efa4bfbfe14a7df54fefe42a40bc233a; expires=Fri, 02 May 2025 16:22:32 GMT; Max-Age=500; path=/ies.sanagustin.sanagustin/",
      "Vary": "Accept-Encoding",
      "Content-Encoding": "gzip",
      "Keep-Alive": "timeout=5, max=99",
      "Connection": "Keep-Alive",
      "Content-Type": "text/html; charset=UTF-8",
      "Strict-Transport-Security": "max-age=15552000",
      "Content-Length": "27009"
   }
}