{
   "test": "ntp_url_web",
   "url": "http://www.educa.madrid.org/ies.anselmolorenzo.sanmartindelavega",
   "delta_sg": -0.363415,
   "cabeceras": {
      "Date": "Tue, 25 Mar 2025 22:35:40 GMT",
      "Server": "Apache",
      "X-Powered-By": "PHP/8.2.25",
      "Link": "<https://site.educa.madrid.org/ies.anselmolorenzo.sanmartindelavega/index.php/wp-json/>; rel=\"https://api.w.org/\"",
      "Set-Cookie": "wc_session_ids[default]=fa777df163d1d520e5f04ea173f979ea1f4387a7; expires=Tue, 25 Mar 2025 22:44:00 GMT; Max-Age=500; path=/ies.anselmolorenzo.sanmartindelavega/; secure; HttpOnly, wc_session_ids[all_forms]=0db442e8f0335f35e045d6e47500548d393693b7; expires=Tue, 25 Mar 2025 22:44:00 GMT; Max-Age=500; path=/ies.anselmolorenzo.sanmartindelavega/; secure; HttpOnly, wc_session_ids[multi][0]=5c5f071128e3b554e16e90995b069f86af8a9fad; expires=Tue, 25 Mar 2025 22:44:00 GMT; Max-Age=500; path=/ies.anselmolorenzo.sanmartindelavega/, wc_session_ids[multi][1]=f655f7b0593d4357b429bfdb8c5969062e021bd8; expires=Tue, 25 Mar 2025 22:44:00 GMT; Max-Age=500; path=/ies.anselmolorenzo.sanmartindelavega/, wc_session_ids[multi][2]=8e90e0f7109aa820a764eb7975c02ddd3fb8282d; expires=Tue, 25 Mar 2025 22:44:00 GMT; Max-Age=500; path=/ies.anselmolorenzo.sanmartindelavega/, wc_session_ids[multi][3]=5f16bae4f95a75915686cace1fca7273d4129601; expires=Tue, 25 Mar 2025 22:44:00 GMT; Max-Age=500; path=/ies.anselmolorenzo.sanmartindelavega/, wc_session_ids[multi][4]=d3136f5091a3f159c5ed2a58b28a0d8e55742e31; expires=Tue, 25 Mar 2025 22:44:00 GMT; Max-Age=500; path=/ies.anselmolorenzo.sanmartindelavega/",
      "Vary": "Accept-Encoding",
      "Content-Encoding": "gzip",
      "Keep-Alive": "timeout=5, max=99",
      "Connection": "Keep-Alive",
      "Content-Type": "text/html; charset=UTF-8",
      "Strict-Transport-Security": "max-age=15552000",
      "Content-Length": "41834"
   }
}