{
   "test": "ntp_url_web",
   "url": "http://www.educa.madrid.org/ies.carlosbousono.majadahonda",
   "delta_sg": -0.066256,
   "cabeceras": {
      "Date": "Mon, 17 Mar 2025 20:36:14 GMT",
      "Server": "Apache",
      "X-Powered-By": "PHP/8.2.25",
      "Link": "<https://site.educa.madrid.org/ies.carlosbousono.majadahonda/index.php/wp-json/>; rel=\"https://api.w.org/\", <https://site.educa.madrid.org/ies.carlosbousono.majadahonda/index.php/wp-json/wp/v2/pages/4291>; rel=\"alternate\"; title=\"JSON\"; type=\"application/json\", <https://site.educa.madrid.org/ies.carlosbousono.majadahonda/>; rel=shortlink",
      "Set-Cookie": "wc_session_ids[default]=3ba0d3f0a5f0b36d01cfbc71ceab9205cb2a652c; expires=Mon, 17 Mar 2025 20:44:34 GMT; Max-Age=500; path=/ies.carlosbousono.majadahonda/; secure; HttpOnly, wc_session_ids[all_forms]=b5b7193ebc0c7ec560da125f6e279718a8527d97; expires=Mon, 17 Mar 2025 20:44:34 GMT; Max-Age=500; path=/ies.carlosbousono.majadahonda/; secure; HttpOnly, wc_session_ids[multi][0]=7e16fcda1f4ce5a720c628161fb0a15805cf7e68; expires=Mon, 17 Mar 2025 20:44:34 GMT; Max-Age=500; path=/ies.carlosbousono.majadahonda/, wc_session_ids[multi][1]=5f3a918df868c439442a93109fddebe5c16f52be; expires=Mon, 17 Mar 2025 20:44:34 GMT; Max-Age=500; path=/ies.carlosbousono.majadahonda/, wc_session_ids[multi][2]=7564e65f6e3b83da3d09ff55820a8fcb84be4ccc; expires=Mon, 17 Mar 2025 20:44:34 GMT; Max-Age=500; path=/ies.carlosbousono.majadahonda/, wc_session_ids[multi][3]=1bf66e9d02357b6fd450f6f682cfed7825fe591a; expires=Mon, 17 Mar 2025 20:44:34 GMT; Max-Age=500; path=/ies.carlosbousono.majadahonda/, wc_session_ids[multi][4]=002ea8e4e8cba08150712b2dec73bc47bd4cb01d; expires=Mon, 17 Mar 2025 20:44:34 GMT; Max-Age=500; path=/ies.carlosbousono.majadahonda/",
      "Vary": "Accept-Encoding",
      "Content-Encoding": "gzip",
      "Keep-Alive": "timeout=5, max=99",
      "Connection": "Keep-Alive",
      "Content-Type": "text/html; charset=UTF-8",
      "Strict-Transport-Security": "max-age=15552000",
      "Content-Length": "27232"
   }
}