{
   "test": "ntp_url_web",
   "url": "http://www.educa.madrid.org/ies.angelcorella.colmenarviejo",
   "delta_sg": 0.195021,
   "cabeceras": {
      "Date": "Thu, 29 May 2025 21:18:57 GMT",
      "Server": "Apache",
      "X-Powered-By": "PHP/8.2.25",
      "Link": "<https://site.educa.madrid.org/ies.angelcorella.colmenarviejo/index.php/wp-json/>; rel=\"https://api.w.org/\", <https://site.educa.madrid.org/ies.angelcorella.colmenarviejo/index.php/wp-json/wp/v2/pages/12>; rel=\"alternate\"; title=\"JSON\"; type=\"application/json\", <https://site.educa.madrid.org/ies.angelcorella.colmenarviejo/>; rel=shortlink",
      "Set-Cookie": "wc_session_ids[default]=2d76ebdbcd8eeaa555db409c9adc943389ab813f; expires=Thu, 29 May 2025 21:27:18 GMT; Max-Age=500; path=/ies.angelcorella.colmenarviejo/; secure; HttpOnly, wc_session_ids[all_forms]=ef35a35f9e6e941e8c6c4189ddda207e5a0fbcef; expires=Thu, 29 May 2025 21:27:18 GMT; Max-Age=500; path=/ies.angelcorella.colmenarviejo/; secure; HttpOnly, wc_session_ids[multi][0]=cb967198d79d49ab729e1b5e9517d964d3d2c04c; expires=Thu, 29 May 2025 21:27:18 GMT; Max-Age=500; path=/ies.angelcorella.colmenarviejo/, wc_session_ids[multi][1]=a20d1e1d9a88f65f16c40300f495e52383bab14e; expires=Thu, 29 May 2025 21:27:18 GMT; Max-Age=500; path=/ies.angelcorella.colmenarviejo/, wc_session_ids[multi][2]=feaa41727ab5aba3025338a43a0249db1d1d478c; expires=Thu, 29 May 2025 21:27:18 GMT; Max-Age=500; path=/ies.angelcorella.colmenarviejo/, wc_session_ids[multi][3]=e5ddf2ab1185532a9466721f66bb8b34f9ae59f3; expires=Thu, 29 May 2025 21:27:18 GMT; Max-Age=500; path=/ies.angelcorella.colmenarviejo/, wc_session_ids[multi][4]=11a1a646be232170d22fe0f8d42ebacf0e4f7e8b; expires=Thu, 29 May 2025 21:27:18 GMT; Max-Age=500; path=/ies.angelcorella.colmenarviejo/",
      "Vary": "Accept-Encoding",
      "Content-Encoding": "gzip",
      "Keep-Alive": "timeout=5, max=99",
      "Connection": "Keep-Alive",
      "Content-Type": "text/html; charset=UTF-8",
      "Strict-Transport-Security": "max-age=15552000",
      "Content-Length": "28436"
   }
}