{
   "test": "ntp_url_web",
   "url": "http://www.educa.madrid.org/ies.alonsoquijano.alcala",
   "delta_sg": -0.640518,
   "cabeceras": {
      "Date": "Sun, 23 Mar 2025 12:05:15 GMT",
      "Server": "Apache",
      "X-Powered-By": "PHP/8.2.25",
      "Link": "<https://site.educa.madrid.org/ies.alonsoquijano.alcala/index.php/wp-json/>; rel=\"https://api.w.org/\", <https://site.educa.madrid.org/ies.alonsoquijano.alcala/index.php/wp-json/wp/v2/pages/1063>; rel=\"alternate\"; title=\"JSON\"; type=\"application/json\", <https://site.educa.madrid.org/ies.alonsoquijano.alcala/>; rel=shortlink",
      "Set-Cookie": "wc_session_ids[default]=7554059b58234701fd4a9c368e906f63318a8223; expires=Sun, 23 Mar 2025 12:13:35 GMT; Max-Age=500; path=/ies.alonsoquijano.alcala/; secure; HttpOnly, wc_session_ids[all_forms]=6e81a0619ae54d62d8d159415f255d0c6a0999ff; expires=Sun, 23 Mar 2025 12:13:35 GMT; Max-Age=500; path=/ies.alonsoquijano.alcala/; secure; HttpOnly, wc_session_ids[multi][0]=769e4b6e51b10ebc18271778cbca3150e54d7b32; expires=Sun, 23 Mar 2025 12:13:35 GMT; Max-Age=500; path=/ies.alonsoquijano.alcala/, wc_session_ids[multi][1]=f05d15241ed146a6522b45681fa1608d61b8dd46; expires=Sun, 23 Mar 2025 12:13:35 GMT; Max-Age=500; path=/ies.alonsoquijano.alcala/, wc_session_ids[multi][2]=dd3c0362c602f6a592a8ee7b0b94c4c5d81cc78b; expires=Sun, 23 Mar 2025 12:13:35 GMT; Max-Age=500; path=/ies.alonsoquijano.alcala/, wc_session_ids[multi][3]=0f96fcdebfbf78b2c3579f6d72744a70f7fe2c50; expires=Sun, 23 Mar 2025 12:13:35 GMT; Max-Age=500; path=/ies.alonsoquijano.alcala/, wc_session_ids[multi][4]=3942c362ff69220682371160e574806791019c43; expires=Sun, 23 Mar 2025 12:13:35 GMT; Max-Age=500; path=/ies.alonsoquijano.alcala/",
      "Vary": "Accept-Encoding",
      "Content-Encoding": "gzip",
      "Keep-Alive": "timeout=5, max=99",
      "Connection": "Keep-Alive",
      "Content-Type": "text/html; charset=UTF-8",
      "Strict-Transport-Security": "max-age=15552000",
      "Content-Length": "19607"
   }
}