{
   "test": "ntp_url_web",
   "url": "http://www.educa.madrid.org/ies.alsatt.algete",
   "delta_sg": -0.242863,
   "cabeceras": {
      "Date": "Fri, 07 Mar 2025 19:25:29 GMT",
      "Server": "Apache",
      "X-Powered-By": "PHP/8.2.25",
      "Link": "<https://site.educa.madrid.org/ies.alsatt.algete/index.php/wp-json/>; rel=\"https://api.w.org/\", <https://site.educa.madrid.org/ies.alsatt.algete/index.php/wp-json/wp/v2/pages/1264>; rel=\"alternate\"; title=\"JSON\"; type=\"application/json\", <https://site.educa.madrid.org/ies.alsatt.algete/>; rel=shortlink",
      "Set-Cookie": "wc_session_ids[default]=b526adb48c7d74bddb7a23922c95fcc0e50ba32a; expires=Fri, 07 Mar 2025 19:33:49 GMT; Max-Age=500; path=/ies.alsatt.algete/; secure; HttpOnly, wc_session_ids[all_forms]=53f1b159826a4f97fa396357035701618e190663; expires=Fri, 07 Mar 2025 19:33:49 GMT; Max-Age=500; path=/ies.alsatt.algete/; secure; HttpOnly, wc_session_ids[multi][0]=ac7298e7de717c041010a138c6a0fd079ea73ad4; expires=Fri, 07 Mar 2025 19:33:49 GMT; Max-Age=500; path=/ies.alsatt.algete/, wc_session_ids[multi][1]=ac8eab90cd6805f84d57f2de127ac46670f58048; expires=Fri, 07 Mar 2025 19:33:49 GMT; Max-Age=500; path=/ies.alsatt.algete/, wc_session_ids[multi][2]=1d32d08bda49f54f3952458da43d8899558ff4b7; expires=Fri, 07 Mar 2025 19:33:49 GMT; Max-Age=500; path=/ies.alsatt.algete/, wc_session_ids[multi][3]=2ce61058e461dbf1a8fdbd110fd13f2328af45e0; expires=Fri, 07 Mar 2025 19:33:49 GMT; Max-Age=500; path=/ies.alsatt.algete/, wc_session_ids[multi][4]=c629e2458a919fab24e028a4e3e2c10105784885; expires=Fri, 07 Mar 2025 19:33:49 GMT; Max-Age=500; path=/ies.alsatt.algete/",
      "Vary": "Accept-Encoding",
      "Content-Encoding": "gzip",
      "Keep-Alive": "timeout=5, max=99",
      "Connection": "Keep-Alive",
      "Content-Type": "text/html; charset=UTF-8",
      "Strict-Transport-Security": "max-age=15552000",
      "Content-Length": "20973"
   }
}