{
   "test": "ntp_url_web",
   "url": "http://www.educa.madrid.org/ies.alsatt.algete",
   "delta_sg": 0.610985,
   "cabeceras": {
      "Date": "Mon, 26 May 2025 20:01:37 GMT",
      "Server": "Apache",
      "X-Powered-By": "PHP/8.2.25",
      "Link": "<https://site.educa.madrid.org/ies.alsatt.algete/index.php/wp-json/>; rel=\"https://api.w.org/\", <https://site.educa.madrid.org/ies.alsatt.algete/index.php/wp-json/wp/v2/pages/1264>; rel=\"alternate\"; title=\"JSON\"; type=\"application/json\", <https://site.educa.madrid.org/ies.alsatt.algete/>; rel=shortlink",
      "Set-Cookie": "wc_session_ids[default]=b1e9812522ab844140fdd8c8684b44de7c603ef0; expires=Mon, 26 May 2025 20:09:57 GMT; Max-Age=500; path=/ies.alsatt.algete/; secure; HttpOnly, wc_session_ids[all_forms]=d4492d609c8572690d6ac9466e88a07656d77792; expires=Mon, 26 May 2025 20:09:57 GMT; Max-Age=500; path=/ies.alsatt.algete/; secure; HttpOnly, wc_session_ids[multi][0]=1928163dc812995e254c985843d647bb1b71b9fc; expires=Mon, 26 May 2025 20:09:57 GMT; Max-Age=500; path=/ies.alsatt.algete/, wc_session_ids[multi][1]=b7f1d31fea23606b7428ee1174a2485b1a93aa3c; expires=Mon, 26 May 2025 20:09:57 GMT; Max-Age=500; path=/ies.alsatt.algete/, wc_session_ids[multi][2]=0d6639a8caf6473af551c61baaaa70a5438c792e; expires=Mon, 26 May 2025 20:09:57 GMT; Max-Age=500; path=/ies.alsatt.algete/, wc_session_ids[multi][3]=1ce6be7d26d32059c5c5740aa00d3d207ba55a27; expires=Mon, 26 May 2025 20:09:57 GMT; Max-Age=500; path=/ies.alsatt.algete/, wc_session_ids[multi][4]=6402440cb36b453c6f058a24000abf19bec31944; expires=Mon, 26 May 2025 20:09:57 GMT; Max-Age=500; path=/ies.alsatt.algete/",
      "Vary": "Accept-Encoding",
      "Content-Encoding": "gzip",
      "Keep-Alive": "timeout=5, max=99",
      "Connection": "Keep-Alive",
      "Content-Type": "text/html; charset=UTF-8",
      "Strict-Transport-Security": "max-age=15552000",
      "Content-Length": "20924"
   }
}