{
   "test": "ntp_url_web",
   "url": "http://www.educa.madrid.org/ies.adolfosuarez.paracuellos",
   "delta_sg": 0.514221,
   "cabeceras": {
      "Date": "Wed, 21 May 2025 21:18:07 GMT",
      "Server": "Apache",
      "X-Powered-By": "PHP/8.2.25",
      "Link": "<https://site.educa.madrid.org/ies.adolfosuarez.paracuellos/index.php/wp-json/>; rel=\"https://api.w.org/\", <https://site.educa.madrid.org/ies.adolfosuarez.paracuellos/index.php/wp-json/wp/v2/pages/5295>; rel=\"alternate\"; title=\"JSON\"; type=\"application/json\", <https://site.educa.madrid.org/ies.adolfosuarez.paracuellos/>; rel=shortlink",
      "Set-Cookie": "wc_session_ids[default]=b1ec4e3f6d4f5e89de99eb1e9310b61c3c66b220; expires=Wed, 21 May 2025 21:26:27 GMT; Max-Age=500; path=/ies.adolfosuarez.paracuellos/; secure; HttpOnly, wc_session_ids[all_forms]=88150d50b103e0e40059ba9634704e84199ce5d0; expires=Wed, 21 May 2025 21:26:27 GMT; Max-Age=500; path=/ies.adolfosuarez.paracuellos/; secure; HttpOnly, wc_session_ids[multi][0]=efee46daacfe6e6d7e90541ddb60394fc778301a; expires=Wed, 21 May 2025 21:26:27 GMT; Max-Age=500; path=/ies.adolfosuarez.paracuellos/, wc_session_ids[multi][1]=0e0f21fad8b22a4b62a1699b3a2f0272890622f4; expires=Wed, 21 May 2025 21:26:27 GMT; Max-Age=500; path=/ies.adolfosuarez.paracuellos/, wc_session_ids[multi][2]=16a4f523713b16065ebab425f852f435b4c017c0; expires=Wed, 21 May 2025 21:26:27 GMT; Max-Age=500; path=/ies.adolfosuarez.paracuellos/, wc_session_ids[multi][3]=0cc77a51b6b9c66ceb7864aa535834fa235d735a; expires=Wed, 21 May 2025 21:26:27 GMT; Max-Age=500; path=/ies.adolfosuarez.paracuellos/, wc_session_ids[multi][4]=091f1b7cc210c0c3f988755cc3430fbad0b8392b; expires=Wed, 21 May 2025 21:26:27 GMT; Max-Age=500; path=/ies.adolfosuarez.paracuellos/",
      "Vary": "Accept-Encoding",
      "Content-Encoding": "gzip",
      "Keep-Alive": "timeout=5, max=99",
      "Connection": "Keep-Alive",
      "Content-Type": "text/html; charset=UTF-8",
      "Strict-Transport-Security": "max-age=15552000",
      "Content-Length": "21044"
   }
}