{
   "test": "ntp_url_web",
   "url": "http://www.educa.madrid.org/ies.alsatt.algete",
   "delta_sg": 1.107591,
   "cabeceras": {
      "Date": "Sat, 03 May 2025 16:42:51 GMT",
      "Server": "Apache",
      "X-Powered-By": "PHP/8.2.25",
      "Link": "<https://site.educa.madrid.org/ies.alsatt.algete/index.php/wp-json/>; rel=\"https://api.w.org/\", <https://site.educa.madrid.org/ies.alsatt.algete/index.php/wp-json/wp/v2/pages/1264>; rel=\"alternate\"; title=\"JSON\"; type=\"application/json\", <https://site.educa.madrid.org/ies.alsatt.algete/>; rel=shortlink",
      "Set-Cookie": "wc_session_ids[default]=6c9b17e1e8124739f94ee6a4fa622e64d0ca7296; expires=Sat, 03 May 2025 16:51:11 GMT; Max-Age=500; path=/ies.alsatt.algete/; secure; HttpOnly, wc_session_ids[all_forms]=80f764464c0cdd89dc10ebca5da79e413be0a749; expires=Sat, 03 May 2025 16:51:11 GMT; Max-Age=500; path=/ies.alsatt.algete/; secure; HttpOnly, wc_session_ids[multi][0]=1948f6c98c8e35f7dc4536d9eb829479480eb9dc; expires=Sat, 03 May 2025 16:51:11 GMT; Max-Age=500; path=/ies.alsatt.algete/, wc_session_ids[multi][1]=af59a41e8dabad7e07d182c7526b7e1be513cd94; expires=Sat, 03 May 2025 16:51:11 GMT; Max-Age=500; path=/ies.alsatt.algete/, wc_session_ids[multi][2]=ed65245b5860beff07fc2867276b306a569c24ba; expires=Sat, 03 May 2025 16:51:11 GMT; Max-Age=500; path=/ies.alsatt.algete/, wc_session_ids[multi][3]=425836d662d36b3420db66a0bb9d285b4f58e517; expires=Sat, 03 May 2025 16:51:11 GMT; Max-Age=500; path=/ies.alsatt.algete/, wc_session_ids[multi][4]=65ba860d4060d313b3c108dfa1e1d7a528211342; expires=Sat, 03 May 2025 16:51:11 GMT; Max-Age=500; path=/ies.alsatt.algete/",
      "Vary": "Accept-Encoding",
      "Content-Encoding": "gzip",
      "Keep-Alive": "timeout=5, max=99",
      "Connection": "Keep-Alive",
      "Content-Type": "text/html; charset=UTF-8",
      "Strict-Transport-Security": "max-age=15552000",
      "Content-Length": "20739"
   }
}