{
   "test": "ntp_url_web",
   "url": "http://www.educa.madrid.org/ies.mariagoyrigoyri.madrid",
   "delta_sg": -0.136023,
   "cabeceras": {
      "Date": "Mon, 19 May 2025 22:16:18 GMT",
      "Server": "Apache",
      "X-Powered-By": "PHP/8.2.25",
      "Link": "<https://site.educa.madrid.org/ies.mariagoyrigoyri.madrid/index.php/wp-json/>; rel=\"https://api.w.org/\", <https://site.educa.madrid.org/ies.mariagoyrigoyri.madrid/index.php/wp-json/wp/v2/pages/116>; rel=\"alternate\"; title=\"JSON\"; type=\"application/json\", <https://site.educa.madrid.org/ies.mariagoyrigoyri.madrid/>; rel=shortlink",
      "Set-Cookie": "wc_session_ids[default]=5dbf8cfb7c50c2f15ed776dd85a28e45d370e6d5; expires=Mon, 19 May 2025 22:24:38 GMT; Max-Age=500; path=/ies.mariagoyrigoyri.madrid/; secure; HttpOnly, wc_session_ids[all_forms]=c7bf8f21be62833806baf4211be6d91d3b1bc5a1; expires=Mon, 19 May 2025 22:24:38 GMT; Max-Age=500; path=/ies.mariagoyrigoyri.madrid/; secure; HttpOnly, wc_session_ids[multi][0]=4bc8fe5bf04cd62bc3bd946336a7c9677349ba77; expires=Mon, 19 May 2025 22:24:38 GMT; Max-Age=500; path=/ies.mariagoyrigoyri.madrid/, wc_session_ids[multi][1]=c93400d0af74365b87baa118b11805db592e58dc; expires=Mon, 19 May 2025 22:24:38 GMT; Max-Age=500; path=/ies.mariagoyrigoyri.madrid/, wc_session_ids[multi][2]=5db42d9380e7d907a6017f17ed4265d9a01be423; expires=Mon, 19 May 2025 22:24:38 GMT; Max-Age=500; path=/ies.mariagoyrigoyri.madrid/, wc_session_ids[multi][3]=42ff6e4d3bc942523f3de9325cbaa93d998ce9e7; expires=Mon, 19 May 2025 22:24:38 GMT; Max-Age=500; path=/ies.mariagoyrigoyri.madrid/, wc_session_ids[multi][4]=f460a548c0d85d3852f2b8e754092ba04ca126e2; expires=Mon, 19 May 2025 22:24:38 GMT; Max-Age=500; path=/ies.mariagoyrigoyri.madrid/",
      "Vary": "Accept-Encoding",
      "Content-Encoding": "gzip",
      "Keep-Alive": "timeout=5, max=99",
      "Connection": "Keep-Alive",
      "Content-Type": "text/html; charset=UTF-8",
      "Strict-Transport-Security": "max-age=15552000",
      "Content-Length": "40344"
   }
}