{
   "test": "web_header_url_web",
   "url": "http://www.educa.madrid.org/ies.lasenda.getafe",
   "Strict-Transport-Security": "max-age=15552000",
   "Content-Security-Policy": null,
   "X-Content-Type-Options": null,
   "X-Frame-Options": null,
   "X-XSS-Protection": null,
   "Referrer-Policy": null,
   "Permissions-Policy": null,
   "Cache-Control": null,
   "Set-Cookie": "wc_session_ids[default]=172a8a62aa464aeae9a4e26ddea3e27d12956a66; expires=Sun, 15 Jun 2025 03:50:22 GMT; Max-Age=500; path=/ies.lasenda.getafe/; secure; HttpOnly, wc_session_ids[all_forms]=71d4756cba591882daf7a4af14ac7c67d5620cd9; expires=Sun, 15 Jun 2025 03:50:22 GMT; Max-Age=500; path=/ies.lasenda.getafe/; secure; HttpOnly, wc_session_ids[multi][0]=07d6d2d92ba0f270545f92efc503c00d068b2843; expires=Sun, 15 Jun 2025 03:50:22 GMT; Max-Age=500; path=/ies.lasenda.getafe/, wc_session_ids[multi][1]=17f47f6c3bfebb9a014f7dbdbad66e2d3511dc67; expires=Sun, 15 Jun 2025 03:50:22 GMT; Max-Age=500; path=/ies.lasenda.getafe/, wc_session_ids[multi][2]=1520074b8afe437f1b1197ff038d796935e43959; expires=Sun, 15 Jun 2025 03:50:22 GMT; Max-Age=500; path=/ies.lasenda.getafe/, wc_session_ids[multi][3]=670f100bbdf93f52f8f54133a72ed260756cf973; expires=Sun, 15 Jun 2025 03:50:22 GMT; Max-Age=500; path=/ies.lasenda.getafe/, wc_session_ids[multi][4]=78b0ca32804b0ce4a7d45d4371653a1d7d6b3727; expires=Sun, 15 Jun 2025 03:50:22 GMT; Max-Age=500; path=/ies.lasenda.getafe/",
   "X-Powered-By": "PHP/8.2.25",
   "Server": "Apache",
   "compliance_Strict-Transport-Security": "OK_max_age,KO_includeSubDomains",
   "compliance_Content-Security-Policy": "KO_Content-Security-Policy",
   "compliance_X-Content-Type-Options": "KO_nosniff",
   "compliance_X-Frame-Options": "KO_X-Frame-Options",
   "compliance_X-XSS-Protection": "KO_X-XSS-Protection",
   "compliance_Referrer-Policy": "KO_Referrer-Policy",
   "compliance_Permissions-Policy": "KO_Permissions-Policy",
   "compliance_Cache-Control": "KO_Cache-Control",
   "compliance_Set-Cookie": "KO_Secure,OK_HttpOnly",
   "compliance_X-Powered-By": "KO_X-Powered-By",
   "compliance_Server": "KO_Server",
   "compliance_score": 0.0
}